torch_anatomy/__init__.py
torch_anatomy/cli.py
torch_anatomy/utils.py
torch_anatomy/visualizer.py
torch_anatomy-0.1.1.dist-info/licenses/LICENSE
torch_anatomy-0.1.1.dist-info/METADATA
torch_anatomy-0.1.1.dist-info/WHEEL
torch_anatomy-0.1.1.dist-info/entry_points.txt
torch_anatomy-0.1.1.dist-info/top_level.txt
torch_anatomy-0.1.1.dist-info/RECORD
