Metadata-Version: 2.4
Name: torch-anatomy
Version: 0.1.1
Summary: Layer-by-layer visualizer for PyTorch models
Author: Harshal Vilas Kale
License: MIT
License-File: LICENSE
Requires-Dist: torch
Requires-Dist: torchvision
Requires-Dist: matplotlib
Requires-Dist: numpy
Requires-Dist: Pillow
Requires-Dist: click
Dynamic: author
Dynamic: description
Dynamic: description-content-type
Dynamic: license
Dynamic: license-file
Dynamic: requires-dist
Dynamic: summary
